lake/__init__.py
lake/attributes/__init__.py
lake/attributes/config_reg_attr.py
lake/attributes/control_signal_attr.py
lake/attributes/formal_attr.py
lake/attributes/range_group.py
lake/attributes/sram_port_attr.py
lake/dsl/edge.py
lake/dsl/helper.py
lake/dsl/hw_top_lake.py
lake/dsl/lake_imports.py
lake/dsl/mem_port.py
lake/dsl/memory.py
lake/dsl/top_lake.py
lake/dsl/dsl_examples/memtile.py
lake/dsl/dsl_examples/pond.py
lake/dsl/dsl_examples/simba.py
lake/models/__init__.py
lake/models/addr_gen_model.py
lake/models/agg_aligner_model.py
lake/models/agg_buff_model.py
lake/models/agg_model.py
lake/models/app_ctrl_model.py
lake/models/chain_model.py
lake/models/demux_reads_model.py
lake/models/input_addr_ctrl_model.py
lake/models/lake_top_model.py
lake/models/model.py
lake/models/output_addr_ctrl_model.py
lake/models/passthru_model.py
lake/models/pipe_reg_model.py
lake/models/prefetcher_model.py
lake/models/reg_fifo_model.py
lake/models/register_file_model.py
lake/models/rw_arbiter_model.py
lake/models/sram_model.py
lake/models/sram_wrapper_model.py
lake/models/sync_groups_model.py
lake/models/tb_model.py
lake/models/tba_model.py
lake/modules/__init__.py
lake/modules/addr_gen.py
lake/modules/agg_aligner.py
lake/modules/agg_only.py
lake/modules/agg_sram_shared.py
lake/modules/aggregation_buffer.py
lake/modules/aggregator.py
lake/modules/app_ctrl.py
lake/modules/cfg_reg_wrapper.py
lake/modules/chain.py
lake/modules/chain_accessor.py
lake/modules/config_reg.py
lake/modules/demux_reads.py
lake/modules/doublebuffer_control.py
lake/modules/fifo_control.py
lake/modules/for_loop.py
lake/modules/input_addr_ctrl.py
lake/modules/linebuffer_control.py
lake/modules/output_addr_ctrl.py
lake/modules/passthru.py
lake/modules/pipe_reg.py
lake/modules/prefetcher.py
lake/modules/reg_fifo.py
lake/modules/register_file.py
lake/modules/rw_arbiter.py
lake/modules/single_port_memory.py
lake/modules/sram.py
lake/modules/sram_control.py
lake/modules/sram_only.py
lake/modules/sram_stub.py
lake_aha-0.0.4.dist-info/LICENSE
lake_aha-0.0.4.dist-info/METADATA
lake_aha-0.0.4.dist-info/WHEEL
lake_aha-0.0.4.dist-info/top_level.txt
lake_aha-0.0.4.dist-info/RECORD
