Metadata-Version: 2.1
Name: lake-aha
Version: 0.0.4
Summary: Memory Generator based on Kratos: The God of War.
Home-page: https://github.com/StanfordAHA/lake
Author: Maxwell Strange
Author-email: mstrange@stanford.edu
License: UNKNOWN
Platform: UNKNOWN
Requires-Python: >=3.5
Requires-Dist: kratos
Requires-Dist: fault
Requires-Dist: magma-lang
Requires-Dist: pytest
